[{"@_fa": "true", "link": [{"@_fa": "true", "@ref": "self", "@href": "https://api.elsevier.com/content/abstract/scopus_id/85060527926"}, {"@_fa": "true", "@ref": "author-affiliation", "@href": "https://api.elsevier.com/content/abstract/scopus_id/85060527926?field=author,affiliation"}, {"@_fa": "true", "@ref": "scopus", "@href": "https://www.scopus.com/inward/record.uri?partnerID=HzOxMe3b&scp=85060527926&origin=inward"}, {"@_fa": "true", "@ref": "scopus-citedby", "@href": "https://www.scopus.com/inward/citedby.uri?partnerID=HzOxMe3b&scp=85060527926&origin=inward"}], "prism:url": "https://api.elsevier.com/content/abstract/scopus_id/85060527926", "dc:identifier": "SCOPUS_ID:85060527926", "eid": "2-s2.0-85060527926", "dc:title": "Intermolecular distance measurement with TNT suppressor on the M13 bacteriophage-based F\u00f6rster resonance energy transfer system", "dc:creator": "Kim I.", "prism:publicationName": "Scientific Reports", "prism:eIssn": "20452322", "prism:volume": "9", "prism:issueIdentifier": "1", "prism:pageRange": null, "prism:coverDate": "2019-12-01", "prism:coverDisplayDate": "1 December 2019", "prism:doi": "10.1038/s41598-018-36990-0", "citedby-count": "1", "affiliation": [{"@_fa": "true", "affilname": "Gwangju Institute of Science and Technology", "affiliation-city": "Gwangju", "affiliation-country": "South Korea"}], "pubmed-id": "30679611", "prism:aggregationType": "Journal", "subtype": "ar", "subtypeDescription": "Article", "article-number": "496", "source-id": "21100200805", "openaccess": "1", "openaccessFlag": true}, {"@_fa": "true", "link": [{"@_fa": "true", "@ref": "self", "@href": "https://api.elsevier.com/content/abstract/scopus_id/85072696043"}, {"@_fa": "true", "@ref": "author-affiliation", "@href": "https://api.elsevier.com/content/abstract/scopus_id/85072696043?field=author,affiliation"}, {"@_fa": "true", "@ref": "scopus", "@href": "https://www.scopus.com/inward/record.uri?partnerID=HzOxMe3b&scp=85072696043&origin=inward"}, {"@_fa": "true", "@ref": "scopus-citedby", "@href": "https://www.scopus.com/inward/citedby.uri?partnerID=HzOxMe3b&scp=85072696043&origin=inward"}], "prism:url": "https://api.elsevier.com/content/abstract/scopus_id/85072696043", "dc:identifier": "SCOPUS_ID:85072696043", "eid": "2-s2.0-85072696043", "dc:title": "Stimulation emission depleted photoacoustic", "dc:creator": "Park S.", "prism:publicationName": "Optics Express", "prism:eIssn": "10944087", "prism:volume": "27", "prism:issueIdentifier": "20", "prism:pageRange": "27841-27850", "prism:coverDate": "2019-09-30", "prism:coverDisplayDate": "30 September 2019", "prism:doi": "10.1364/OE.27.027841", "citedby-count": "0", "affiliation": [{"@_fa": "true", "affilname": "Pusan National University", "affiliation-city": "Busan", "affiliation-country": "South Korea"}], "pubmed-id": "31684545", "prism:aggregationType": "Journal", "subtype": "ar", "subtypeDescription": "Article", "source-id": "12862", "openaccess": "0", "openaccessFlag": false}, {"@_fa": "true", "link": [{"@_fa": "true", "@ref": "self", "@href": "https://api.elsevier.com/content/abstract/scopus_id/85070391832"}, {"@_fa": "true", "@ref": "author-affiliation", "@href": "https://api.elsevier.com/content/abstract/scopus_id/85070391832?field=author,affiliation"}, {"@_fa": "true", "@ref": "scopus", "@href": "https://www.scopus.com/inward/record.uri?partnerID=HzOxMe3b&scp=85070391832&origin=inward"}, {"@_fa": "true", "@ref": "scopus-citedby", "@href": "https://www.scopus.com/inward/citedby.uri?partnerID=HzOxMe3b&scp=85070391832&origin=inward"}], "prism:url": "https://api.elsevier.com/content/abstract/scopus_id/85070391832", "dc:identifier": "SCOPUS_ID:85070391832", "eid": "2-s2.0-85070391832", "dc:title": "Two-step energy transfer dynamics in conjugated polymer and dye-labeled aptamer-based potassium ion detection assay", "dc:creator": "Kim I.", "prism:publicationName": "Polymers", "prism:eIssn": "20734360", "prism:volume": "11", "prism:issueIdentifier": "7", "prism:pageRange": null, "prism:coverDate": "2019-07-01", "prism:coverDisplayDate": "1 July 2019", "prism:doi": "10.3390/polym11071206", "citedby-count": "1", "affiliation": [{"@_fa": "true", "affilname": "Gwangju Institute of Science and Technology", "affiliation-city": "Gwangju", "affiliation-country": "South Korea"}], "prism:aggregationType": "Journal", "subtype": "ar", "subtypeDescription": "Article", "article-number": "1206", "source-id": "54222", "openaccess": "1", "openaccessFlag": true}, {"@_fa": "true", "link": [{"@_fa": "true", "@ref": "self", "@href": "https://api.elsevier.com/content/abstract/scopus_id/85062368510"}, {"@_fa": "true", "@ref": "author-affiliation", "@href": "https://api.elsevier.com/content/abstract/scopus_id/85062368510?field=author,affiliation"}, {"@_fa": "true", "@ref": "scopus", "@href": "https://www.scopus.com/inward/record.uri?partnerID=HzOxMe3b&scp=85062368510&origin=inward"}, {"@_fa": "true", "@ref": "scopus-citedby", "@href": "https://www.scopus.com/inward/citedby.uri?partnerID=HzOxMe3b&scp=85062368510&origin=inward"}], "prism:url": "https://api.elsevier.com/content/abstract/scopus_id/85062368510", "dc:identifier": "SCOPUS_ID:85062368510", "eid": "2-s2.0-85062368510", "dc:title": "Optical gain of inelastic exciton-exciton scattering in CdS nanowires", "dc:creator": "Jang J.", "prism:publicationName": "Applied Physics Letters", "prism:issn": "00036951", "prism:volume": "114", "prism:issueIdentifier": "8", "prism:pageRange": null, "prism:coverDate": "2019-02-25", "prism:coverDisplayDate": "25 February 2019", "prism:doi": "10.1063/1.5086782", "citedby-count": "0", "affiliation": [{"@_fa": "true", "affilname": "Pusan National University", "affiliation-city": "Busan", "affiliation-country": "South Korea"}], "prism:aggregationType": "Journal", "subtype": "ar", "subtypeDescription": "Article", "article-number": "081101", "source-id": "27030", "openaccess": "0", "openaccessFlag": false}, {"@_fa": "true", "link": [{"@_fa": "true", "@ref": "self", "@href": "https://api.elsevier.com/content/abstract/scopus_id/85069493415"}, {"@_fa": "true", "@ref": "author-affiliation", "@href": "https://api.elsevier.com/content/abstract/scopus_id/85069493415?field=author,affiliation"}, {"@_fa": "true", "@ref": "scopus", "@href": "https://www.scopus.com/inward/record.uri?partnerID=HzOxMe3b&scp=85069493415&origin=inward"}, {"@_fa": "true", "@ref": "scopus-citedby", "@href": "https://www.scopus.com/inward/citedby.uri?partnerID=HzOxMe3b&scp=85069493415&origin=inward"}], "prism:url": "https://api.elsevier.com/content/abstract/scopus_id/85069493415", "dc:identifier": "SCOPUS_ID:85069493415", "eid": "2-s2.0-85069493415", "dc:title": "Shape ellipticity dependence of exciton fine levels and optical nonlinearities in CdSe and CdTe nanocrystal quantum dots", "dc:creator": "Yang H.", "prism:publicationName": "Current Optics and Photonics", "prism:issn": "25087266", "prism:eIssn": "25087274", "prism:volume": "3", "prism:issueIdentifier": "2", "prism:pageRange": "143-149", "prism:coverDate": "2019-01-01", "prism:coverDisplayDate": "2019", "prism:doi": "10.3807/COPP.2019.3.2.143", "citedby-count": "0", "affiliation": [{"@_fa": "true", "affilname": "Pusan National University", "affiliation-city": "Busan", "affiliation-country": "South Korea"}], "prism:aggregationType": "Journal", "subtype": "ar", "subtypeDescription": "Article", "source-id": "21100831043", "openaccess": "0", "openaccessFlag": false}, {"@_fa": "true", "link": [{"@_fa": "true", "@ref": "self", "@href": "https://api.elsevier.com/content/abstract/scopus_id/85055204629"}, {"@_fa": "true", "@ref": "author-affiliation", "@href": "https://api.elsevier.com/content/abstract/scopus_id/85055204629?field=author,affiliation"}, {"@_fa": "true", "@ref": "scopus", "@href": "https://www.scopus.com/inward/record.uri?partnerID=HzOxMe3b&scp=85055204629&origin=inward"}, {"@_fa": "true", "@ref": "scopus-citedby", "@href": "https://www.scopus.com/inward/citedby.uri?partnerID=HzOxMe3b&scp=85055204629&origin=inward"}], "prism:url": "https://api.elsevier.com/content/abstract/scopus_id/85055204629", "dc:identifier": "SCOPUS_ID:85055204629", "eid": "2-s2.0-85055204629", "dc:title": "Modeling Quantum Beats by Degenerate Four-Wave Mixing Spectroscopy in a Single GaAs/AlGaAs Quantum Ring", "dc:creator": "Je K.", "prism:publicationName": "Physica Status Solidi - Rapid Research Letters", "prism:issn": "18626254", "prism:eIssn": "18626270", "prism:volume": "13", "prism:issueIdentifier": "1", "prism:pageRange": null, "prism:coverDate": "2019-01-01", "prism:coverDisplayDate": "January 2019", "prism:doi": "10.1002/pssr.201800354", "citedby-count": "1", "affiliation": [{"@_fa": "true", "affilname": "SS Cyril and Methodius University", "affiliation-city": "Skopje", "affiliation-country": "North Macedonia"}, {"@_fa": "true", "affilname": "Pusan National University", "affiliation-city": "Busan", "affiliation-country": "South Korea"}], "prism:aggregationType": "Journal", "subtype": "ar", "subtypeDescription": "Article", "article-number": "1800354", "source-id": "10400153302", "openaccess": "1", "openaccessFlag": true}, {"@_fa": "true", "link": [{"@_fa": "true", "@ref": "self", "@href": "https://api.elsevier.com/content/abstract/scopus_id/85053887609"}, {"@_fa": "true", "@ref": "author-affiliation", "@href": "https://api.elsevier.com/content/abstract/scopus_id/85053887609?field=author,affiliation"}, {"@_fa": "true", "@ref": "scopus", "@href": "https://www.scopus.com/inward/record.uri?partnerID=HzOxMe3b&scp=85053887609&origin=inward"}, {"@_fa": "true", "@ref": "scopus-citedby", "@href": "https://www.scopus.com/inward/citedby.uri?partnerID=HzOxMe3b&scp=85053887609&origin=inward"}], "prism:url": "https://api.elsevier.com/content/abstract/scopus_id/85053887609", "dc:identifier": "SCOPUS_ID:85053887609", "eid": "2-s2.0-85053887609", "dc:title": "Light Controlled Optical Aharonov-Bohm Oscillations in a Single Quantum Ring", "dc:creator": "Kim H.", "prism:publicationName": "Nano Letters", "prism:issn": "15306984", "prism:eIssn": "15306992", "prism:volume": "18", "prism:issueIdentifier": "10", "prism:pageRange": "6188-6194", "prism:coverDate": "2018-10-10", "prism:coverDisplayDate": "10 October 2018", "prism:doi": "10.1021/acs.nanolett.8b02131", "citedby-count": "4", "affiliation": [{"@_fa": "true", "affilname": "University of Oxford", "affiliation-city": "Oxford", "affiliation-country": "United Kingdom"}, {"@_fa": "true", "affilname": "Northeast Normal University", "affiliation-city": "Changchun", "affiliation-country": "China"}], "pubmed-id": "30223652", "prism:aggregationType": "Journal", "subtype": "ar", "subtypeDescription": "Article", "source-id": "17853", "openaccess": "0", "openaccessFlag": false}, {"@_fa": "true", "link": [{"@_fa": "true", "@ref": "self", "@href": "https://api.elsevier.com/content/abstract/scopus_id/85053011729"}, {"@_fa": "true", "@ref": "author-affiliation", "@href": "https://api.elsevier.com/content/abstract/scopus_id/85053011729?field=author,affiliation"}, {"@_fa": "true", "@ref": "scopus", "@href": "https://www.scopus.com/inward/record.uri?partnerID=HzOxMe3b&scp=85053011729&origin=inward"}, {"@_fa": "true", "@ref": "scopus-citedby", "@href": "https://www.scopus.com/inward/citedby.uri?partnerID=HzOxMe3b&scp=85053011729&origin=inward"}], "prism:url": "https://api.elsevier.com/content/abstract/scopus_id/85053011729", "dc:identifier": "SCOPUS_ID:85053011729", "eid": "2-s2.0-85053011729", "dc:title": "Decoherence Dynamics of Localized States in a Single GaAs/AlGaAs Quantum Ring", "dc:creator": "Kim M.", "prism:publicationName": "Physica Status Solidi - Rapid Research Letters", "prism:issn": "18626254", "prism:eIssn": "18626270", "prism:volume": "12", "prism:issueIdentifier": "9", "prism:pageRange": null, "prism:coverDate": "2018-09-01", "prism:coverDisplayDate": "September 2018", "prism:doi": "10.1002/pssr.201800176", "citedby-count": "1", "affiliation": [{"@_fa": "true", "affilname": "Pusan National University", "affiliation-city": "Busan", "affiliation-country": "South Korea"}], "prism:aggregationType": "Journal", "subtype": "ar", "subtypeDescription": "Article", "article-number": "1800176", "source-id": "10400153302", "openaccess": "0", "openaccessFlag": false}, {"@_fa": "true", "link": [{"@_fa": "true", "@ref": "self", "@href": "https://api.elsevier.com/content/abstract/scopus_id/85051644828"}, {"@_fa": "true", "@ref": "author-affiliation", "@href": "https://api.elsevier.com/content/abstract/scopus_id/85051644828?field=author,affiliation"}, {"@_fa": "true", "@ref": "scopus", "@href": "https://www.scopus.com/inward/record.uri?partnerID=HzOxMe3b&scp=85051644828&origin=inward"}, {"@_fa": "true", "@ref": "scopus-citedby", "@href": "https://www.scopus.com/inward/citedby.uri?partnerID=HzOxMe3b&scp=85051644828&origin=inward"}], "prism:url": "https://api.elsevier.com/content/abstract/scopus_id/85051644828", "dc:identifier": "SCOPUS_ID:85051644828", "eid": "2-s2.0-85051644828", "dc:title": "Carrier Relaxation Dynamics Between Localized Vertical Confinement States in GaAs/AlGaAs Quantum Rings", "dc:creator": "Park S.", "prism:publicationName": "Journal of the Korean Physical Society", "prism:issn": "03744884", "prism:eIssn": "19768524", "prism:volume": "73", "prism:issueIdentifier": "3", "prism:pageRange": "314-319", "prism:coverDate": "2018-08-01", "prism:coverDisplayDate": "1 August 2018", "prism:doi": "10.3938/jkps.73.314", "citedby-count": "0", "affiliation": [{"@_fa": "true", "affilname": "Pusan National University", "affiliation-city": "Busan", "affiliation-country": "South Korea"}], "prism:aggregationType": "Journal", "subtype": "ar", "subtypeDescription": "Article", "source-id": "28637", "openaccess": "0", "openaccessFlag": false}, {"@_fa": "true", "link": [{"@_fa": "true", "@ref": "self", "@href": "https://api.elsevier.com/content/abstract/scopus_id/85047916803"}, {"@_fa": "true", "@ref": "author-affiliation", "@href": "https://api.elsevier.com/content/abstract/scopus_id/85047916803?field=author,affiliation"}, {"@_fa": "true", "@ref": "scopus", "@href": "https://www.scopus.com/inward/record.uri?partnerID=HzOxMe3b&scp=85047916803&origin=inward"}, {"@_fa": "true", "@ref": "scopus-citedby", "@href": "https://www.scopus.com/inward/citedby.uri?partnerID=HzOxMe3b&scp=85047916803&origin=inward"}], "prism:url": "https://api.elsevier.com/content/abstract/scopus_id/85047916803", "dc:identifier": "SCOPUS_ID:85047916803", "eid": "2-s2.0-85047916803", "dc:title": "Magnetic field insensitive photoluminescence decay of ZnSe/CdS core/shell type-II colloidal quantum dots", "dc:creator": "Lee W.", "prism:publicationName": "Japanese Journal of Applied Physics", "prism:issn": "00214922", "prism:eIssn": "13474065", "prism:volume": "57", "prism:issueIdentifier": "6", "prism:pageRange": null, "prism:coverDate": "2018-06-01", "prism:coverDisplayDate": "June 2018", "prism:doi": "10.7567/JJAP.57.06HE06", "citedby-count": "1", "affiliation": [{"@_fa": "true", "affilname": "Pusan National University", "affiliation-city": "Busan", "affiliation-country": "South Korea"}], "prism:aggregationType": "Journal", "subtype": "cp", "subtypeDescription": "Conference Paper", "article-number": "06HE06", "source-id": "130262", "openaccess": "0", "openaccessFlag": false}, {"@_fa": "true", "link": [{"@_fa": "true", "@ref": "self", "@href": "https://api.elsevier.com/content/abstract/scopus_id/85069523128"}, {"@_fa": "true", "@ref": "author-affiliation", "@href": "https://api.elsevier.com/content/abstract/scopus_id/85069523128?field=author,affiliation"}, {"@_fa": "true", "@ref": "scopus", "@href": "https://www.scopus.com/inward/record.uri?partnerID=HzOxMe3b&scp=85069523128&origin=inward"}, {"@_fa": "true", "@ref": "scopus-citedby", "@href": "https://www.scopus.com/inward/citedby.uri?partnerID=HzOxMe3b&scp=85069523128&origin=inward"}], "prism:url": "https://api.elsevier.com/content/abstract/scopus_id/85069523128", "dc:identifier": "SCOPUS_ID:85069523128", "eid": "2-s2.0-85069523128", "dc:title": "Two-dimensional nature of center-of-mass excitons confined in a single CdMnTe/CdTe/CdMnTe heterostructure", "dc:creator": "Lee W.", "prism:publicationName": "Current Optics and Photonics", "prism:issn": "25087266", "prism:eIssn": "25087274", "prism:volume": "2", "prism:issueIdentifier": "6", "prism:pageRange": "589-594", "prism:coverDate": "2018-01-01", "prism:coverDisplayDate": "2018", "prism:doi": "10.3807/COPP.2018.2.6.589", "citedby-count": "0", "affiliation": [{"@_fa": "true", "affilname": "Pusan National University", "affiliation-city": "Busan", "affiliation-country": "South Korea"}], "prism:aggregationType": "Journal", "subtype": "ar", "subtypeDescription": "Article", "source-id": "21100831043", "openaccess": "0", "openaccessFlag": false}, {"@_fa": "true", "link": [{"@_fa": "true", "@ref": "self", "@href": "https://api.elsevier.com/content/abstract/scopus_id/85052878058"}, {"@_fa": "true", "@ref": "author-affiliation", "@href": "https://api.elsevier.com/content/abstract/scopus_id/85052878058?field=author,affiliation"}, {"@_fa": "true", "@ref": "scopus", "@href": "https://www.scopus.com/inward/record.uri?partnerID=HzOxMe3b&scp=85052878058&origin=inward"}, {"@_fa": "true", "@ref": "scopus-citedby", "@href": "https://www.scopus.com/inward/citedby.uri?partnerID=HzOxMe3b&scp=85052878058&origin=inward"}], "prism:url": "https://api.elsevier.com/content/abstract/scopus_id/85052878058", "dc:identifier": "SCOPUS_ID:85052878058", "eid": "2-s2.0-85052878058", "dc:title": "Optical Aharonov-Bohm Oscillations with Disorder Effects and Wigner Molecule in a Single GaAs/AlGaAs Quantum Ring", "dc:creator": "Kyhm K.", "prism:publicationName": "NanoScience and Technology", "prism:issn": "14344904", "prism:pageRange": "231-254", "prism:coverDate": "2018-01-01", "prism:coverDisplayDate": "2018", "prism:doi": "10.1007/978-3-319-95159-1_9", "citedby-count": "0", "affiliation": [{"@_fa": "true", "affilname": "Pusan National University", "affiliation-city": "Busan", "affiliation-country": "South Korea"}], "prism:aggregationType": "Book Series", "subtype": "ch", "subtypeDescription": "Chapter", "source-id": "21100216986", "openaccess": "0", "openaccessFlag": false}, {"@_fa": "true", "link": [{"@_fa": "true", "@ref": "self", "@href": "https://api.elsevier.com/content/abstract/scopus_id/85034446003"}, {"@_fa": "true", "@ref": "author-affiliation", "@href": "https://api.elsevier.com/content/abstract/scopus_id/85034446003?field=author,affiliation"}, {"@_fa": "true", "@ref": "scopus", "@href": "https://www.scopus.com/inward/record.uri?partnerID=HzOxMe3b&scp=85034446003&origin=inward"}, {"@_fa": "true", "@ref": "scopus-citedby", "@href": "https://www.scopus.com/inward/citedby.uri?partnerID=HzOxMe3b&scp=85034446003&origin=inward"}], "prism:url": "https://api.elsevier.com/content/abstract/scopus_id/85034446003", "dc:identifier": "SCOPUS_ID:85034446003", "eid": "2-s2.0-85034446003", "dc:title": "Excitation polarization dependence of optical coupled exciton states in a single coupled quantum dot molecule", "dc:creator": "Kim H.", "prism:publicationName": "Journal of Physics: Conference Series", "prism:issn": "17426588", "prism:eIssn": "17426596", "prism:volume": "906", "prism:issueIdentifier": "1", "prism:pageRange": null, "prism:coverDate": "2017-10-22", "prism:coverDisplayDate": "22 October 2017", "prism:doi": "10.1088/1742-6596/906/1/012006", "citedby-count": "1", "affiliation": [{"@_fa": "true", "affilname": "Hokkaido University", "affiliation-city": "Sapporo", "affiliation-country": "Japan"}], "prism:aggregationType": "Conference Proceeding", "subtype": "cp", "subtypeDescription": "Conference Paper", "article-number": "012006", "source-id": "130053", "openaccess": "1", "openaccessFlag": true}, {"@_fa": "true", "link": [{"@_fa": "true", "@ref": "self", "@href": "https://api.elsevier.com/content/abstract/scopus_id/85034862074"}, {"@_fa": "true", "@ref": "author-affiliation", "@href": "https://api.elsevier.com/content/abstract/scopus_id/85034862074?field=author,affiliation"}, {"@_fa": "true", "@ref": "scopus", "@href": "https://www.scopus.com/inward/record.uri?partnerID=HzOxMe3b&scp=85034862074&origin=inward"}, {"@_fa": "true", "@ref": "scopus-citedby", "@href": "https://www.scopus.com/inward/citedby.uri?partnerID=HzOxMe3b&scp=85034862074&origin=inward"}], "prism:url": "https://api.elsevier.com/content/abstract/scopus_id/85034862074", "dc:identifier": "SCOPUS_ID:85034862074", "eid": "2-s2.0-85034862074", "dc:title": "Surface plasmon-assisted photoluminescence enhancement of Au-hybrid CdSe/ZnS nanocrystal quantum dots", "dc:creator": "Kim I.", "prism:publicationName": "Molecular Crystals and Liquid Crystals", "prism:issn": "15421406", "prism:eIssn": "15635287", "prism:volume": "654", "prism:issueIdentifier": "1", "prism:pageRange": "1-5", "prism:coverDate": "2017-09-02", "prism:coverDisplayDate": "2 September 2017", "prism:doi": "10.1080/15421406.2017.1348202", "citedby-count": "0", "affiliation": [{"@_fa": "true", "affilname": "Pusan National University", "affiliation-city": "Busan", "affiliation-country": "South Korea"}], "prism:aggregationType": "Journal", "subtype": "ar", "subtypeDescription": "Article", "source-id": "24711", "openaccess": "0", "openaccessFlag": false}, {"@_fa": "true", "link": [{"@_fa": "true", "@ref": "self", "@href": "https://api.elsevier.com/content/abstract/scopus_id/85026797404"}, {"@_fa": "true", "@ref": "author-affiliation", "@href": "https://api.elsevier.com/content/abstract/scopus_id/85026797404?field=author,affiliation"}, {"@_fa": "true", "@ref": "scopus", "@href": "https://www.scopus.com/inward/record.uri?partnerID=HzOxMe3b&scp=85026797404&origin=inward"}, {"@_fa": "true", "@ref": "scopus-citedby", "@href": "https://www.scopus.com/inward/citedby.uri?partnerID=HzOxMe3b&scp=85026797404&origin=inward"}], "prism:url": "https://api.elsevier.com/content/abstract/scopus_id/85026797404", "dc:identifier": "SCOPUS_ID:85026797404", "eid": "2-s2.0-85026797404", "dc:title": "Optical sectioning in optical resolution photo acoustic microscopy", "dc:creator": "Park S.", "prism:publicationName": "Optics Express", "prism:eIssn": "10944087", "prism:volume": "25", "prism:issueIdentifier": "16", "prism:pageRange": "18917-18928", "prism:coverDate": "2017-08-07", "prism:coverDisplayDate": "7 August 2017", "prism:doi": "10.1364/OE.25.018917", "citedby-count": "7", "affiliation": [{"@_fa": "true", "affilname": "Pusan National University", "affiliation-city": "Busan", "affiliation-country": "South Korea"}], "pubmed-id": "29041083", "prism:aggregationType": "Journal", "subtype": "ar", "subtypeDescription": "Article", "source-id": "12862", "openaccess": "0", "openaccessFlag": false}, {"@_fa": "true", "link": [{"@_fa": "true", "@ref": "self", "@href": "https://api.elsevier.com/content/abstract/scopus_id/84987942293"}, {"@_fa": "true", "@ref": "author-affiliation", "@href": "https://api.elsevier.com/content/abstract/scopus_id/84987942293?field=author,affiliation"}, {"@_fa": "true", "@ref": "scopus", "@href": "https://www.scopus.com/inward/record.uri?partnerID=HzOxMe3b&scp=84987942293&origin=inward"}, {"@_fa": "true", "@ref": "scopus-citedby", "@href": "https://www.scopus.com/inward/citedby.uri?partnerID=HzOxMe3b&scp=84987942293&origin=inward"}, {"@_fa": "true", "@ref": "full-text", "@href": "https://api.elsevier.com/content/article/eid/1-s2.0-S0925400516314514"}], "prism:url": "https://api.elsevier.com/content/abstract/scopus_id/84987942293", "dc:identifier": "SCOPUS_ID:84987942293", "eid": "2-s2.0-84987942293", "dc:title": "Inhibitor effects on molecular beacon-based mercury assays for tuning of detection range", "dc:creator": "Le V.", "prism:publicationName": "Sensors and Actuators, B: Chemical", "prism:issn": "09254005", "prism:volume": "240", "prism:pageRange": "810-817", "prism:coverDate": "2017-03-01", "prism:coverDisplayDate": "1 March 2017", "prism:doi": "10.1016/j.snb.2016.09.034", "pii": "S0925400516314514", "citedby-count": "4", "affiliation": [{"@_fa": "true", "affilname": "Pusan National University", "affiliation-city": "Busan", "affiliation-country": "South Korea"}], "prism:aggregationType": "Journal", "subtype": "ar", "subtypeDescription": "Article", "source-id": "25236", "openaccess": "0", "openaccessFlag": false}, {"@_fa": "true", "link": [{"@_fa": "true", "@ref": "self", "@href": "https://api.elsevier.com/content/abstract/scopus_id/85029685513"}, {"@_fa": "true", "@ref": "author-affiliation", "@href": "https://api.elsevier.com/content/abstract/scopus_id/85029685513?field=author,affiliation"}, {"@_fa": "true", "@ref": "scopus", "@href": "https://www.scopus.com/inward/record.uri?partnerID=HzOxMe3b&scp=85029685513&origin=inward"}, {"@_fa": "true", "@ref": "scopus-citedby", "@href": "https://www.scopus.com/inward/citedby.uri?partnerID=HzOxMe3b&scp=85029685513&origin=inward"}], "prism:url": "https://api.elsevier.com/content/abstract/scopus_id/85029685513", "dc:identifier": "SCOPUS_ID:85029685513", "eid": "2-s2.0-85029685513", "dc:title": "All-optical polarization phase modulation in coupled quantum dots", "dc:creator": "Je K.", "prism:publicationName": "Current Optics and Photonics", "prism:issn": "25087266", "prism:eIssn": "25087274", "prism:volume": "1", "prism:issueIdentifier": "1", "prism:pageRange": "60-64", "prism:coverDate": "2017-02-01", "prism:coverDisplayDate": "February 2017", "prism:doi": "10.3807/COPP.2017.1.1.060", "citedby-count": "0", "affiliation": [{"@_fa": "true", "affilname": "Anyang University", "affiliation-city": "Anyang", "affiliation-country": "South Korea"}, {"@_fa": "true", "affilname": "Pusan National University", "affiliation-city": "Busan", "affiliation-country": "South Korea"}], "prism:aggregationType": "Journal", "subtype": "ar", "subtypeDescription": "Article", "source-id": "21100831043", "openaccess": "1", "openaccessFlag": true}, {"@_fa": "true", "link": [{"@_fa": "true", "@ref": "self", "@href": "https://api.elsevier.com/content/abstract/scopus_id/85008391614"}, {"@_fa": "true", "@ref": "author-affiliation", "@href": "https://api.elsevier.com/content/abstract/scopus_id/85008391614?field=author,affiliation"}, {"@_fa": "true", "@ref": "scopus", "@href": "https://www.scopus.com/inward/record.uri?partnerID=HzOxMe3b&scp=85008391614&origin=inward"}, {"@_fa": "true", "@ref": "scopus-citedby", "@href": "https://www.scopus.com/inward/citedby.uri?partnerID=HzOxMe3b&scp=85008391614&origin=inward"}], "prism:url": "https://api.elsevier.com/content/abstract/scopus_id/85008391614", "dc:identifier": "SCOPUS_ID:85008391614", "eid": "2-s2.0-85008391614", "dc:title": "Quasi-one-dimensional density of states in a single quantum ring", "dc:creator": "Kim H.", "prism:publicationName": "Scientific Reports", "prism:eIssn": "20452322", "prism:volume": "7", "prism:pageRange": null, "prism:coverDate": "2017-01-05", "prism:coverDisplayDate": "5 January 2017", "prism:doi": "10.1038/srep40026", "pii": "srep40026", "citedby-count": "15", "affiliation": [{"@_fa": "true", "affilname": "University of Oxford", "affiliation-city": "Oxford", "affiliation-country": "United Kingdom"}, {"@_fa": "true", "affilname": "Pusan National University", "affiliation-city": "Busan", "affiliation-country": "South Korea"}], "pubmed-id": "28053350", "prism:aggregationType": "Journal", "subtype": "ar", "subtypeDescription": "Article", "article-number": "40026", "source-id": "21100200805", "openaccess": "1", "openaccessFlag": true}, {"@_fa": "true", "link": [{"@_fa": "true", "@ref": "self", "@href": "https://api.elsevier.com/content/abstract/scopus_id/85006511425"}, {"@_fa": "true", "@ref": "author-affiliation", "@href": "https://api.elsevier.com/content/abstract/scopus_id/85006511425?field=author,affiliation"}, {"@_fa": "true", "@ref": "scopus", "@href": "https://www.scopus.com/inward/record.uri?partnerID=HzOxMe3b&scp=85006511425&origin=inward"}, {"@_fa": "true", "@ref": "scopus-citedby", "@href": "https://www.scopus.com/inward/citedby.uri?partnerID=HzOxMe3b&scp=85006511425&origin=inward"}], "prism:url": "https://api.elsevier.com/content/abstract/scopus_id/85006511425", "dc:identifier": "SCOPUS_ID:85006511425", "eid": "2-s2.0-85006511425", "dc:title": "Exciton Dipole-Dipole Interaction in a Single Coupled-Quantum-Dot Structure via Polarized Excitation", "dc:creator": "Kim H.", "prism:publicationName": "Nano Letters", "prism:issn": "15306984", "prism:eIssn": "15306992", "prism:volume": "16", "prism:issueIdentifier": "12", "prism:pageRange": "7755-7760", "prism:coverDate": "2016-12-14", "prism:coverDisplayDate": "14 December 2016", "prism:doi": "10.1021/acs.nanolett.6b03868", "citedby-count": "11", "affiliation": [{"@_fa": "true", "affilname": "University of Oxford", "affiliation-city": "Oxford", "affiliation-country": "United Kingdom"}, {"@_fa": "true", "affilname": "Pusan National University", "affiliation-city": "Busan", "affiliation-country": "South Korea"}], "prism:aggregationType": "Journal", "subtype": "ar", "subtypeDescription": "Article", "source-id": "17853", "openaccess": "0", "openaccessFlag": false}, {"@_fa": "true", "link": [{"@_fa": "true", "@ref": "self", "@href": "https://api.elsevier.com/content/abstract/scopus_id/84957843833"}, {"@_fa": "true", "@ref": "author-affiliation", "@href": "https://api.elsevier.com/content/abstract/scopus_id/84957843833?field=author,affiliation"}, {"@_fa": "true", "@ref": "scopus", "@href": "https://www.scopus.com/inward/record.uri?partnerID=HzOxMe3b&scp=84957843833&origin=inward"}, {"@_fa": "true", "@ref": "scopus-citedby", "@href": "https://www.scopus.com/inward/citedby.uri?partnerID=HzOxMe3b&scp=84957843833&origin=inward"}], "prism:url": "https://api.elsevier.com/content/abstract/scopus_id/84957843833", "dc:identifier": "SCOPUS_ID:84957843833", "eid": "2-s2.0-84957843833", "dc:title": "Enhancement of the photoluminescence properties of Ba<inf>1.98</inf>SiO<inf>4\u2212\u03b4</inf>N<inf>2/3\u03b4</inf>:Eu<inf>0.02</inf> phosphors and their application to green LEDs", "dc:creator": "Wang S.", "prism:publicationName": "Journal of Materials Science: Materials in Electronics", "prism:issn": "09574522", "prism:eIssn": "1573482X", "prism:volume": "27", "prism:issueIdentifier": "3", "prism:pageRange": "2809-2815", "prism:coverDate": "2016-03-01", "prism:coverDisplayDate": "1 March 2016", "prism:doi": "10.1007/s10854-015-4094-9", "citedby-count": "1", "affiliation": [{"@_fa": "true", "affilname": "Pusan National University", "affiliation-city": "Busan", "affiliation-country": "South Korea"}], "prism:aggregationType": "Journal", "subtype": "ar", "subtypeDescription": "Article", "source-id": "21177", "openaccess": "0", "openaccessFlag": false}, {"@_fa": "true", "link": [{"@_fa": "true", "@ref": "self", "@href": "https://api.elsevier.com/content/abstract/scopus_id/84957590944"}, {"@_fa": "true", "@ref": "author-affiliation", "@href": "https://api.elsevier.com/content/abstract/scopus_id/84957590944?field=author,affiliation"}, {"@_fa": "true", "@ref": "scopus", "@href": "https://www.scopus.com/inward/record.uri?partnerID=HzOxMe3b&scp=84957590944&origin=inward"}, {"@_fa": "true", "@ref": "scopus-citedby", "@href": "https://www.scopus.com/inward/citedby.uri?partnerID=HzOxMe3b&scp=84957590944&origin=inward"}], "prism:url": "https://api.elsevier.com/content/abstract/scopus_id/84957590944", "dc:identifier": "SCOPUS_ID:84957590944", "eid": "2-s2.0-84957590944", "dc:title": "Observation of a Biexciton Wigner Molecule by Fractional Optical Aharonov-Bohm Oscillations in a Single Quantum Ring", "dc:creator": "Kim H.", "prism:publicationName": "Nano Letters", "prism:issn": "15306984", "prism:eIssn": "15306992", "prism:volume": "16", "prism:issueIdentifier": "1", "prism:pageRange": "27-33", "prism:coverDate": "2016-01-13", "prism:coverDisplayDate": "13 January 2016", "prism:doi": "10.1021/acs.nanolett.5b02419", "citedby-count": "27", "affiliation": [{"@_fa": "true", "affilname": "University of Oxford", "affiliation-city": "Oxford", "affiliation-country": "United Kingdom"}, {"@_fa": "true", "affilname": "Pusan National University", "affiliation-city": "Busan", "affiliation-country": "South Korea"}], "prism:aggregationType": "Journal", "subtype": "ar", "subtypeDescription": "Article", "source-id": "17853", "openaccess": "0", "openaccessFlag": false}, {"@_fa": "true", "link": [{"@_fa": "true", "@ref": "self", "@href": "https://api.elsevier.com/content/abstract/scopus_id/84962788651"}, {"@_fa": "true", "@ref": "author-affiliation", "@href": "https://api.elsevier.com/content/abstract/scopus_id/84962788651?field=author,affiliation"}, {"@_fa": "true", "@ref": "scopus", "@href": "https://www.scopus.com/inward/record.uri?partnerID=HzOxMe3b&scp=84962788651&origin=inward"}, {"@_fa": "true", "@ref": "scopus-citedby", "@href": "https://www.scopus.com/inward/citedby.uri?partnerID=HzOxMe3b&scp=84962788651&origin=inward"}], "prism:url": "https://api.elsevier.com/content/abstract/scopus_id/84962788651", "dc:identifier": "SCOPUS_ID:84962788651", "eid": "2-s2.0-84962788651", "dc:title": "Polarization dependence and optical Aharonov-Bohm oscillations in a single local QR in a large droplet QD", "dc:creator": "Park S.H.", "prism:publicationName": "2015 11th Conference on Lasers and Electro-Optics Pacific Rim, CLEO-PR 2015", "prism:isbn": [{"@_fa": "true", "$": "9781467371094"}], "prism:volume": "3", "prism:pageRange": null, "prism:coverDate": "2016-01-07", "prism:coverDisplayDate": "7 January 2016", "prism:doi": "10.1109/CLEOPR.2015.7376565", "citedby-count": "0", "affiliation": [{"@_fa": "true", "affilname": "Pusan National University", "affiliation-city": "Busan", "affiliation-country": "South Korea"}], "prism:aggregationType": "Conference Proceeding", "subtype": "cp", "subtypeDescription": "Conference Paper", "article-number": "7376565", "source-id": "21100455482", "openaccess": "0", "openaccessFlag": false}, {"@_fa": "true", "link": [{"@_fa": "true", "@ref": "self", "@href": "https://api.elsevier.com/content/abstract/scopus_id/84930965872"}, {"@_fa": "true", "@ref": "author-affiliation", "@href": "https://api.elsevier.com/content/abstract/scopus_id/84930965872?field=author,affiliation"}, {"@_fa": "true", "@ref": "scopus", "@href": "https://www.scopus.com/inward/record.uri?partnerID=HzOxMe3b&scp=84930965872&origin=inward"}, {"@_fa": "true", "@ref": "scopus-citedby", "@href": "https://www.scopus.com/inward/citedby.uri?partnerID=HzOxMe3b&scp=84930965872&origin=inward"}, {"@_fa": "true", "@ref": "full-text", "@href": "https://api.elsevier.com/content/article/eid/1-s2.0-S1010603015001975"}], "prism:url": "https://api.elsevier.com/content/abstract/scopus_id/84930965872", "dc:identifier": "SCOPUS_ID:84930965872", "eid": "2-s2.0-84930965872", "dc:title": "Photosensitization of novel ruthenium-functionalized photoconductive polymers: Effect of ruthenium complex as photosensitizer", "dc:creator": "Moon J.", "prism:publicationName": "Journal of Photochemistry and Photobiology A: Chemistry", "prism:issn": "10106030", "prism:volume": "310", "prism:pageRange": "141-147", "prism:coverDate": "2015-06-10", "prism:coverDisplayDate": "10 June 2015", "prism:doi": "10.1016/j.jphotochem.2015.05.032", "pii": "S1010603015001975", "citedby-count": "4", "affiliation": [{"@_fa": "true", "affilname": "Pusan National University", "affiliation-city": "Busan", "affiliation-country": "South Korea"}], "prism:aggregationType": "Journal", "subtype": "ar", "subtypeDescription": "Article", "source-id": "26966", "openaccess": "0", "openaccessFlag": false}, {"@_fa": "true", "link": [{"@_fa": "true", "@ref": "self", "@href": "https://api.elsevier.com/content/abstract/scopus_id/84938704414"}, {"@_fa": "true", "@ref": "author-affiliation", "@href": "https://api.elsevier.com/content/abstract/scopus_id/84938704414?field=author,affiliation"}, {"@_fa": "true", "@ref": "scopus", "@href": "https://www.scopus.com/inward/record.uri?partnerID=HzOxMe3b&scp=84938704414&origin=inward"}, {"@_fa": "true", "@ref": "scopus-citedby", "@href": "https://www.scopus.com/inward/citedby.uri?partnerID=HzOxMe3b&scp=84938704414&origin=inward"}], "prism:url": "https://api.elsevier.com/content/abstract/scopus_id/84938704414", "dc:identifier": "SCOPUS_ID:84938704414", "eid": "2-s2.0-84938704414", "dc:title": "Solvent-modified ultrafast decay dynamics in conjugated polymer/dye labeled single stranded DNA", "dc:creator": "Kim I.", "prism:publicationName": "Progress in Biomedical Optics and Imaging - Proceedings of SPIE", "prism:issn": "16057422", "prism:isbn": [{"@_fa": "true", "$": "9781628416794"}], "prism:volume": "9523", "prism:pageRange": null, "prism:coverDate": "2015-01-01", "prism:coverDisplayDate": "2015", "prism:doi": "10.1117/12.2190332", "citedby-count": "0", "affiliation": [{"@_fa": "true", "affilname": "Pusan National University", "affiliation-city": "Busan", "affiliation-country": "South Korea"}], "prism:aggregationType": "Conference Proceeding", "subtype": "cp", "subtypeDescription": "Conference Paper", "article-number": "95230N", "source-id": "130022", "openaccess": "0", "openaccessFlag": false}, {"@_fa": "true", "link": [{"@_fa": "true", "@ref": "self", "@href": "https://api.elsevier.com/content/abstract/scopus_id/84938521958"}, {"@_fa": "true", "@ref": "author-affiliation", "@href": "https://api.elsevier.com/content/abstract/scopus_id/84938521958?field=author,affiliation"}, {"@_fa": "true", "@ref": "scopus", "@href": "https://www.scopus.com/inward/record.uri?partnerID=HzOxMe3b&scp=84938521958&origin=inward"}, {"@_fa": "true", "@ref": "scopus-citedby", "@href": "https://www.scopus.com/inward/citedby.uri?partnerID=HzOxMe3b&scp=84938521958&origin=inward"}, {"@_fa": "true", "@ref": "full-text", "@href": "https://api.elsevier.com/content/article/eid/1-s2.0-S1567173915000796"}], "prism:url": "https://api.elsevier.com/content/abstract/scopus_id/84938521958", "dc:identifier": "SCOPUS_ID:84938521958", "eid": "2-s2.0-84938521958", "dc:title": "Polarization anisotropy of exciton in self-assembled elliptical InP/InGaP quantum dots", "dc:creator": "Kim I.", "prism:publicationName": "Current Applied Physics", "prism:issn": "15671739", "prism:volume": "15", "prism:issueIdentifier": "6", "prism:pageRange": "733-738", "prism:coverDate": "2015-01-01", "prism:coverDisplayDate": "2015", "prism:doi": "10.1016/j.cap.2015.03.002", "pii": "S1567173915000796", "citedby-count": "6", "affiliation": [{"@_fa": "true", "affilname": "Pusan National University", "affiliation-city": "Busan", "affiliation-country": "South Korea"}], "prism:aggregationType": "Journal", "subtype": "ar", "subtypeDescription": "Article", "source-id": "27477", "openaccess": "0", "openaccessFlag": false}]